_pyngraph.cpython-38-darwin.so
requirements.txt
ngraph/__init__.py
ngraph/exceptions.py
ngraph/helpers.py
ngraph/opset_utils.py
ngraph/impl/__init__.py
ngraph/impl/op/__init__.py
ngraph/impl/op/util/__init__.py
ngraph/impl/passes/__init__.py
ngraph/opset1/__init__.py
ngraph/opset1/ops.py
ngraph/opset2/__init__.py
ngraph/opset2/ops.py
ngraph/opset3/__init__.py
ngraph/opset3/ops.py
ngraph/opset4/__init__.py
ngraph/opset4/ops.py
ngraph/opset5/__init__.py
ngraph/opset5/ops.py
ngraph/opset6/__init__.py
ngraph/opset6/ops.py
ngraph/opset7/__init__.py
ngraph/opset7/ops.py
ngraph/opset8/__init__.py
ngraph/opset8/ops.py
ngraph/utils/__init__.py
ngraph/utils/broadcasting.py
ngraph/utils/decorators.py
ngraph/utils/input_validation.py
ngraph/utils/node_factory.py
ngraph/utils/reduction.py
ngraph/utils/tensor_iterator_types.py
ngraph/utils/types.py
openvino/__init__.py
openvino/pyopenvino.cpython-38-darwin.so
openvino/utils.py
openvino/frontend/__init__.py
openvino/frontend/onnx/__init__.py
openvino/frontend/onnx/py_onnx_frontend.cpython-38-darwin.so
openvino/frontend/paddle/__init__.py
openvino/frontend/paddle/py_paddle_frontend.cpython-38-darwin.so
openvino/frontend/tensorflow/__init__.py
openvino/inference_engine/__init__.py
openvino/inference_engine/constants.so
openvino/inference_engine/ie_api.so
openvino/libs/libopenvino.dylib
openvino/libs/libopenvino_arm_cpu_plugin.so
openvino/libs/libopenvino_auto_batch_plugin.so
openvino/libs/libopenvino_auto_plugin.so
openvino/libs/libopenvino_gapi_preproc.so
openvino/libs/libopenvino_hetero_plugin.so
openvino/libs/libopenvino_ir_frontend.dylib
openvino/libs/libopenvino_onnx_frontend.dylib
openvino/libs/libopenvino_paddle_frontend.dylib
openvino/libs/libopenvino_tensorflow_fe.dylib
openvino/libs/plugins.xml
openvino/offline_transformations/__init__.py
openvino/preprocess/__init__.py
openvino/runtime/__init__.py
openvino/runtime/exceptions.py
openvino/runtime/ie_api.py
openvino/runtime/opset_utils.py
openvino/runtime/op/__init__.py
openvino_arm-2022.1.0.1.dist-info/LICENSE
openvino_arm-2022.1.0.1.dist-info/METADATA
openvino_arm-2022.1.0.1.dist-info/WHEEL
openvino_arm-2022.1.0.1.dist-info/onednn_third-party-programs.txt
openvino_arm-2022.1.0.1.dist-info/readme.txt
openvino_arm-2022.1.0.1.dist-info/runtime-third-party-programs.txt
openvino_arm-2022.1.0.1.dist-info/tbb_third-party-programs.txt
openvino_arm-2022.1.0.1.dist-info/top_level.txt
openvino_arm-2022.1.0.1.dist-info/RECORD
