Metadata-Version: 2.1
Name: openvino-arm
Version: 2022.1.0.1
Summary: OpenVINO(TM) Runtime
Home-page: https://github.com/cansik/openvino-arm
Download-URL: https://github.com/openvinotoolkit/openvino/tags
Author: Intel(R) Corporation
Author-email: openvino_pushbot@intel.com
License: OSI Approved :: Apache Software License
Platform: UNKNOWN
License-File: readme.txt
License-File: LICENSE
License-File: ../../../../licensing/runtime-third-party-programs.txt
License-File: ../../../../licensing/tbb_third-party-programs.txt
License-File: ../../../../licensing/onednn_third-party-programs.txt
Requires-Dist: numpy (>=1.16.6)
